{
  "/start": "Привет, давай сыграем в игру 'Камень-ножницы-бумага'",
  "/help": "Правила игры:\nТы можешь выбрать на виртуальной клавиатуре кнопку, которая будет присылать в чат тескт с либо ножницами, либо бумагой, либо камнем. Я [Бот] буду тоже выкидывать текст с любым из этих предметов. Комбинации выигрыша следующие:\nКамень бьет ножницы\nНожницы бьют бумагу\nБумага бьет камень\nНу что, хочешь сыграть?",
  "any_unexpected_commands": "Я не понимаю из того, что ты написал",
  "play_the_game": "Отлично! Делай свой выбор!",
  "not_play_the_game": "Хорошо. Если, вдруг, захочешь сыграть - открой клавиатуру и нажми \"Давай!",
  "total_of_the_game": ["Победил ", "Если хочешь сыграть еще, то нажми 'Давай'"],
  "inline_keyboards": {
    "choice_to_play_the_game_kb": ["Давай", "Не хочу"],
    "choice_of_item_kb": ["Камень", "Ножницы", "Бумага"]
  },
  "winners": ["Никто", "я", "ты"]

}